huhk/__init__.py
huhk/init_project.py
huhk/main.py
huhk/setup_run.py
huhk/unit_apache_beam.py
huhk/unit_data.py
huhk/unit_dict.py
huhk/unit_encryption.py
huhk/unit_faker.py
huhk/unit_fun.py
huhk/unit_logger.py
huhk/unit_redis.py
huhk/unit_request.py
huhk/unit_selenium.py
huhk/unit_tasks.py
huhk/常用命令.py
huhk/allure-2.23.1/bin/allure
huhk/allure-2.23.1/bin/allure.bat
huhk/allure-2.23.1/config/allure-cucumber.yml
huhk/allure-2.23.1/config/allure-junit.yml
huhk/allure-2.23.1/config/allure.yml
huhk/allure-2.23.1/lib/allure-commandline-2.23.1.jar
huhk/allure-2.23.1/lib/allure-generator-2.23.1.jar
huhk/allure-2.23.1/lib/allure-model-2.23.0.jar
huhk/allure-2.23.1/lib/allure-plugin-api-2.23.1.jar
huhk/allure-2.23.1/lib/allure1-model-1.0.jar
huhk/allure-2.23.1/lib/annotations-15.0.jar
huhk/allure-2.23.1/lib/commons-beanutils-1.9.4.jar
huhk/allure-2.23.1/lib/commons-codec-1.11.jar
huhk/allure-2.23.1/lib/commons-collections-3.2.2.jar
huhk/allure-2.23.1/lib/commons-collections4-4.2.jar
huhk/allure-2.23.1/lib/commons-io-2.13.0.jar
huhk/allure-2.23.1/lib/commons-lang3-3.12.0.jar
huhk/allure-2.23.1/lib/commons-logging-1.2.jar
huhk/allure-2.23.1/lib/commons-text-1.3.jar
huhk/allure-2.23.1/lib/flexmark-0.62.2.jar
huhk/allure-2.23.1/lib/flexmark-ext-tables-0.62.2.jar
huhk/allure-2.23.1/lib/flexmark-util-0.62.2.jar
huhk/allure-2.23.1/lib/flexmark-util-ast-0.62.2.jar
huhk/allure-2.23.1/lib/flexmark-util-builder-0.62.2.jar
huhk/allure-2.23.1/lib/flexmark-util-collection-0.62.2.jar
huhk/allure-2.23.1/lib/flexmark-util-data-0.62.2.jar
huhk/allure-2.23.1/lib/flexmark-util-dependency-0.62.2.jar
huhk/allure-2.23.1/lib/flexmark-util-format-0.62.2.jar
huhk/allure-2.23.1/lib/flexmark-util-html-0.62.2.jar
huhk/allure-2.23.1/lib/flexmark-util-misc-0.62.2.jar
huhk/allure-2.23.1/lib/flexmark-util-options-0.62.2.jar
huhk/allure-2.23.1/lib/flexmark-util-sequence-0.62.2.jar
huhk/allure-2.23.1/lib/flexmark-util-visitor-0.62.2.jar
huhk/allure-2.23.1/lib/freemarker-2.3.32.jar
huhk-3.9.5.dist-info/METADATA
huhk-3.9.5.dist-info/WHEEL
huhk-3.9.5.dist-info/entry_points.txt
huhk-3.9.5.dist-info/top_level.txt
huhk-3.9.5.dist-info/RECORD
