Metadata-Version: 2.1
Name: huhk
Version: 3.9.5
Summary: 接口自动化
Home-page: UNKNOWN
Author: 胡杭凯
Author-email: 3173825608@qq.com
License: UNKNOWN
Platform: UNKNOWN
Requires-Python: >=3.0
Requires-Dist: faker
Requires-Dist: openpyxl
Requires-Dist: apscheduler
Requires-Dist: rsa
Requires-Dist: pyDes
Requires-Dist: pycryptodome
Requires-Dist: xlsxwriter
Requires-Dist: pandas
Requires-Dist: apache-beam
Requires-Dist: pytest
Requires-Dist: setuptools
Requires-Dist: twine
Requires-Dist: requests (==2.29.0)
Requires-Dist: click
Requires-Dist: allure-pytest
Requires-Dist: pytest-rerunfailures
Requires-Dist: pytest-instafail
Requires-Dist: python-gitlab
Requires-Dist: xlwt
Requires-Dist: xlrd
Requires-Dist: redis
